audit_logging_pepsico/Kafka_log.py
audit_logging_pepsico/audit.py
audit_logging_pepsico/audit_config.py
audit_logging_pepsico/constants.py
audit_logging_pepsico/kafka_utilities.py
audit_logging_pepsico-1.0.1.dist-info/LICENSE
audit_logging_pepsico-1.0.1.dist-info/METADATA
audit_logging_pepsico-1.0.1.dist-info/WHEEL
audit_logging_pepsico-1.0.1.dist-info/top_level.txt
audit_logging_pepsico-1.0.1.dist-info/RECORD
