Metadata-Version: 2.1
Name: audit-logging-pepsico
Version: 1.0.1
Summary: A logging package which allows users to log in pepsico format. Specially write logs for request and response.
Author-email: Jatin Talati <jatalati@in.ibm.com>
Keywords: logging,audit,pepsico,kafka,couchbase
Classifier: Programming Language :: Python :: 3
Classifier: Development Status :: 1 - Planning
Classifier: Operating System :: OS Independent
Requires-Python: >=3.7
License-File: LICENSE
Requires-Dist: azure-core
Requires-Dist: azure-storage-blob
Requires-Dist: toml
